{
  "saveWindowLocations": true,
  "useCustomWindowName": false,
  "customWindowName": "Second Window",
  "windows": {
    "Second Window": {
      "hosts": {
        "Kyle_Laptop": {
          "x": 3456,
          "y": -216,
          "width": 640,
          "height": 672,
          "fullscreen": false,
          "maximized": false
        },
        "KylesDesktop": {
          "x": -8,
          "y": -8,
          "width": 2576,
          "height": 1408,
          "fullscreen": false,
          "maximized": true
        }
      }
    }
  }
}