{"Conclusion":{"Conclusion":{"currentFile":{"count":1,"lastUpdated":1762358604757}}},"pf2e/creature/type/human":{"pf2e/creature/type/human":{"frontMatter":{"count":3,"lastUpdated":1762578941002}}},"pf2e/creature/type/aberration":{"pf2e/creature/type/aberration":{"frontMatter":{"count":2,"lastUpdated":1764206914377}}},"pf2e/creature/type/time":{"pf2e/creature/type/time":{"frontMatter":{"count":1,"lastUpdated":1762551064161}}},"invisibility":{"invisibility":{"internalLink":{"count":1,"lastUpdated":1762551958184}}},"haste":{"haste":{"internalLink":{"count":1,"lastUpdated":1762551978042}}},"slow":{"slow":{"internalLink":{"count":1,"lastUpdated":1762551987221}}},"2d10+14":{"2d10+14":{"currentFile":{"count":1,"lastUpdated":1764188090309}}},"trait/magical":{"trait/magical":{"frontMatter":{"count":2,"lastUpdated":1764188935422}}},"teleportation":{"teleportation":{"internalLink":{"count":1,"lastUpdated":1764188962026}}},"trait/complex":{"trait/complex":{"frontMatter":{"count":1,"lastUpdated":1764189003689}}},"pf2e/creature/type/ooze":{"pf2e/creature/type/ooze":{"frontMatter":{"count":1,"lastUpdated":1764206951127}}},"trait/divine":{"trait/divine":{"frontMatter":{"count":1,"lastUpdated":1764212366522}}},"rhythmic":{"rhythmic":{"currentFile":{"count":1,"lastUpdated":1764213513596}}},"The Crystalline Queen":{"sairazul-logm":{"internalLink":{"count":1,"lastUpdated":1764213624146}}},"Winter":{"Winter":{"internalLink":{"count":1,"lastUpdated":1764214239206}}},"Ediza":{"Ediza":{"internalLink":{"count":1,"lastUpdated":1764218545790}}},"Kassandra Voice of Kataklysmos":{"Kassandra Voice of Kataklysmos":{"internalLink":{"count":1,"lastUpdated":1764223574537}}}}